[
    {
        "coleccion": "151",
        "title": "Charizard",
        "precio": "45.99",
        "imageFilename": "coleccion-151/charizard.png"
    },
    {
        "coleccion": "151",
        "title": "Mew",
        "precio": "89.99",
        "imageFilename": "coleccion-151/mew.png"
    },
    {
        "coleccion": "Black Bolt",
        "title": "Victini",
        "precio": "32.99",
        "imageFilename": "coleccion-blackbolt/victini.png"
    },
    {
        "coleccion": "Black Bolt",
        "title": "Zekrom",
        "precio": "67.99",
        "imageFilename": "coleccion-blackbolt/zekrom.png"
    },
    {
        "coleccion": "Legendary Treasures",
        "title": "Meloetta",
        "precio": "55.99",
        "imageFilename": "coleccion-legendarytreasures/meloetta.jfif"
    },
    {
        "coleccion": "Legendary Treasures",
        "title": "Swablu",
        "precio": "12.99",
        "imageFilename": "coleccion-legendarytreasures/swablu.jfif"
    },
    {
        "coleccion": "Paradox Rift",
        "title": "Groudon",
        "precio": "78.99",
        "imageFilename": "coleccion-paradoxrift/groudon.jfif"
    },
    {
        "coleccion": "Paradox Rift",
        "title": "Yveltal",
        "precio": "69.99",
        "imageFilename": "coleccion-paradoxrift/yveltal.jfif"
    },
    {
        "coleccion": "Plasma Storm",
        "title": "Klinklang",
        "precio": "35.99",
        "imageFilename": "coleccion-plasmastorm/klinklang.jfif"
    },
    {
        "coleccion": "Plasma Storm",
        "title": "Zapdos",
        "precio": "52.99",
        "imageFilename": "coleccion-plasmastorm/zapdos.jfif"
    },
    {
        "coleccion": "Crown Zenith",
        "title": "Giratina",
        "precio": "95.99",
        "imageFilename": "coleccion.crownzenit/giratina.jfif"
    },
    {
        "coleccion": "Crown Zenith",
        "title": "Magmortar",
        "precio": "42.99",
        "imageFilename": "coleccion.crownzenit/magmortar.jfif"
    }
]